ckastro/__init__.py
ckastro/__main__.py
ckastro/io/__init__.py
ckastro/io/subcube.py
ck_astro-0.0.1.dist-info/LICENSE
ck_astro-0.0.1.dist-info/METADATA
ck_astro-0.0.1.dist-info/WHEEL
ck_astro-0.0.1.dist-info/top_level.txt
ck_astro-0.0.1.dist-info/RECORD
